{
  "finish": {
    "simpleMeaning": "Do the last part and stop",
    "contextMeaning": "End your job time at 6 p.m",
    "sentence": "You finish work at 6 p.m."
  },
  "work": {
    "simpleMeaning": "Things you do to earn money",
    "contextMeaning": "Your job or tasks at your job",
    "sentence": "You finish work at 6 p.m."
  },
  "boss": {
    "simpleMeaning": "The person who tells workers what to do",
    "contextMeaning": "The person in charge at your job",
    "sentence": "Your boss wants one last email to a big client."
  },
  "wants": {
    "simpleMeaning": "Needs or would like something",
    "contextMeaning": "Needs you to send one more email",
    "sentence": "Your boss wants one last email to a big client."
  },
  "one": {
    "simpleMeaning": "A single thing or person",
    "contextMeaning": "Just a single email",
    "sentence": "Your boss wants one last email to a big client."
  },
  "last": {
    "simpleMeaning": "Coming at the end",
    "contextMeaning": "The final email before stopping",
    "sentence": "Your boss wants one last email to a big client."
  },
  "email": {
    "simpleMeaning": "A message sent on a computer or phone",
    "contextMeaning": "A short message sent to a client",
    "sentence": "Your boss wants one last email to a big client."
  },
  "big": {
    "simpleMeaning": "Large in size or amount",
    "contextMeaning": "Important or large in size",
    "sentence": "Your boss wants one last email to a big client."
  },
  "client": {
    "simpleMeaning": "A person who buys help or services",
    "contextMeaning": "A customer for your company",
    "sentence": "Your boss wants one last email to a big client."
  },
  "open": {
    "simpleMeaning": "Make something not closed",
    "contextMeaning": "Start using the AI tool",
    "sentence": "You open an AI tool and ask for help."
  },
  "ai": {
    "simpleMeaning": "A smart computer helper",
    "contextMeaning": "A computer program that helps you",
    "sentence": "You open an AI tool and ask for help."
  },
  "tool": {
    "simpleMeaning": "Something that helps you do a job",
    "contextMeaning": "A computer helper you use",
    "sentence": "You open an AI tool and ask for help."
  },
  "ask": {
    "simpleMeaning": "Say you want something or need something",
    "contextMeaning": "Tell the tool you need help",
    "sentence": "You open an AI tool and ask for help."
  },
  "help": {
    "simpleMeaning": "Make something easier for someone",
    "contextMeaning": "Support from the AI tool",
    "sentence": "You open an AI tool and ask for help."
  },
  "ten": {
    "simpleMeaning": "The number after nine",
    "contextMeaning": "10 seconds",
    "sentence": "In ten seconds, you get a perfect message."
  },
  "seconds": {
    "simpleMeaning": "A very short time, like a tiny moment",
    "contextMeaning": "A very short time before the message is ready",
    "sentence": "In ten seconds, you get a perfect message."
  },
  "get": {
    "simpleMeaning": "To have or receive something",
    "contextMeaning": "You receive a perfect message",
    "sentence": "In ten seconds, you get a perfect message."
  },
  "perfect": {
    "simpleMeaning": "Very, very good; no mistakes",
    "contextMeaning": "Very good and with no mistakes",
    "sentence": "In ten seconds, you get a perfect message."
  },
  "message": {
    "simpleMeaning": "Words sent to someone",
    "contextMeaning": "A short text or email you send to someone",
    "sentence": "In ten seconds, you get a perfect message."
  },
  "tone": {
    "simpleMeaning": "The feeling in your words",
    "contextMeaning": "How the words sound to other people",
    "sentence": "The tone is polite."
  },
  "polite": {
    "simpleMeaning": "Kind and good-mannered",
    "contextMeaning": "Kind and respectful",
    "sentence": "The tone is polite."
  },
  "grammar": {
    "simpleMeaning": "The rules for making correct sentences",
    "contextMeaning": "The sentence rules are correct",
    "sentence": "The grammar is clean."
  },
  "clean": {
    "simpleMeaning": "Neat and not dirty",
    "contextMeaning": "Neat and without mistakes",
    "sentence": "The grammar is clean."
  },
  "then": {
    "simpleMeaning": "After that; next",
    "contextMeaning": "After that moment",
    "sentence": "Then you notice one line: the delivery date is wrong."
  },
  "notice": {
    "simpleMeaning": "To see or realize something",
    "contextMeaning": "To see that one line has a problem",
    "sentence": "Then you notice one line: the delivery date is wrong."
  },
  "line": {
    "simpleMeaning": "A row of words",
    "contextMeaning": "One row of words in the email",
    "sentence": "Then you notice one line: the delivery date is wrong."
  },
  "delivery": {
    "simpleMeaning": "Bringing something to a place",
    "contextMeaning": "Bringing the package to someone",
    "sentence": "Then you notice one line: the delivery date is wrong."
  },
  "date": {
    "simpleMeaning": "A day on the calendar",
    "contextMeaning": "The day the package should arrive",
    "sentence": "Then you notice one line: the delivery date is wrong."
  },
  "wrong": {
    "simpleMeaning": "Not right; a mistake",
    "contextMeaning": "Not correct",
    "sentence": "Then you notice one line: the delivery date is wrong."
  },
  "now": {
    "simpleMeaning": "At this time; right away",
    "contextMeaning": "At this time, in the present",
    "sentence": "Now you have a real problem."
  },
  "real": {
    "simpleMeaning": "True, not fake or pretend",
    "contextMeaning": "True, not fake; actual, not just imagined",
    "sentence": "Now you have a real problem."
  },
  "problem": {
    "simpleMeaning": "Something bad that needs help",
    "contextMeaning": "A difficult thing that needs fixing",
    "sentence": "Now you have a real problem."
  },
  "send": {
    "simpleMeaning": "Make something go to someone",
    "contextMeaning": "To make the message go to someone",
    "sentence": "Do you send it fast, or do you stop and check?"
  },
  "fast": {
    "simpleMeaning": "Very quick, not slow",
    "contextMeaning": "Quickly, with little time",
    "sentence": "Do you send it fast, or do you stop and check?"
  },
  "stop": {
    "simpleMeaning": "Not move or do it anymore",
    "contextMeaning": "To pause before doing the next thing",
    "sentence": "Do you send it fast, or do you stop and check?"
  },
  "check": {
    "simpleMeaning": "Look carefully to see if it is right",
    "contextMeaning": "Look carefully to make sure it is right",
    "sentence": "Do you send it fast, or do you stop and check?"
  },
  "new": {
    "simpleMeaning": "Not old; made or seen before now",
    "contextMeaning": "A different kind that people have not used before",
    "sentence": "This is a new kind of work skill."
  },
  "kind": {
    "simpleMeaning": "A type or sort of thing",
    "contextMeaning": "A type of work skill",
    "sentence": "This is a new kind of work skill."
  },
  "skill": {
    "simpleMeaning": "Something you can do well",
    "contextMeaning": "An ability people can learn and use at work",
    "sentence": "This is a new kind of work skill."
  },
  "only": {
    "simpleMeaning": "Just this one thing, not more",
    "contextMeaning": "Just using AI, not other things",
    "sentence": "It is not only using AI."
  },
  "using": {
    "simpleMeaning": "Doing something with a thing",
    "contextMeaning": "Doing something with AI",
    "sentence": "It is not only using AI."
  },
  "wisely": {
    "simpleMeaning": "In a smart and careful way",
    "contextMeaning": "In a smart and careful way",
    "sentence": "It is using it wisely."
  },
  "week": {
    "simpleMeaning": "Seven days together",
    "contextMeaning": "The seven days before now",
    "sentence": "Last week, Maria, who works at a small shipping company in Manila, had a busy afternoon."
  },
  "maria": {
    "simpleMeaning": "A girl's name",
    "contextMeaning": "The woman in the story",
    "sentence": "Last week, Maria, who works at a small shipping company in Manila, had a busy afternoon."
  },
  "who": {
    "simpleMeaning": "Used for a person in a sentence",
    "contextMeaning": "Shows which person is being talked about",
    "sentence": "Last week, Maria, who works at a small shipping company in Manila, had a busy afternoon."
  },
  "works": {
    "simpleMeaning": "Has a job and does tasks there",
    "contextMeaning": "Has a job at the shipping company",
    "sentence": "Last week, Maria, who works at a small shipping company in Manila, had a busy afternoon."
  },
  "small": {
    "simpleMeaning": "Not big",
    "contextMeaning": "Not big",
    "sentence": "Last week, Maria, who works at a small shipping company in Manila, had a busy afternoon."
  },
  "shipping": {
    "simpleMeaning": "Moving things to other places",
    "contextMeaning": "About sending goods to people",
    "sentence": "Last week, Maria, who works at a small shipping company in Manila, had a busy afternoon."
  },
  "company": {
    "simpleMeaning": "A group of people who work together",
    "contextMeaning": "The business Maria works for",
    "sentence": "Last week, Maria, who works at a small shipping company in Manila, had a busy afternoon."
  },
  "manila": {
    "simpleMeaning": "A city name",
    "contextMeaning": "The city where Maria works",
    "sentence": "Last week, Maria, who works at a small shipping company in Manila, had a busy afternoon."
  },
  "busy": {
    "simpleMeaning": "Having many things to do",
    "contextMeaning": "Having many things to do that afternoon",
    "sentence": "Last week, Maria, who works at a small shipping company in Manila, had a busy afternoon."
  },
  "afternoon": {
    "simpleMeaning": "Time after lunch and before evening",
    "contextMeaning": "The time later in the day",
    "sentence": "Last week, Maria, who works at a small shipping company in Manila, had a busy afternoon."
  },
  "storm": {
    "simpleMeaning": "Very bad weather with wind and rain",
    "contextMeaning": "Bad weather that stopped the trucks",
    "sentence": "A storm had delayed several trucks."
  },
  "delayed": {
    "simpleMeaning": "Made later than planned",
    "contextMeaning": "Made the trucks arrive later",
    "sentence": "A storm had delayed several trucks."
  },
  "several": {
    "simpleMeaning": "More than two, but not many",
    "contextMeaning": "A few trucks",
    "sentence": "A storm had delayed several trucks."
  },
  "trucks": {
    "simpleMeaning": "Big cars that carry things",
    "contextMeaning": "Big vehicles carrying goods",
    "sentence": "A storm had delayed several trucks."
  },
  "customers": {
    "simpleMeaning": "People who buy things or use a service",
    "contextMeaning": "People buying or asking for help",
    "sentence": "Customers were calling every few minutes."
  },
  "calling": {
    "simpleMeaning": "Talking on the phone",
    "contextMeaning": "Phoning again and again",
    "sentence": "Customers were calling every few minutes."
  },
  "every": {
    "simpleMeaning": "All of them, one by one",
    "contextMeaning": "Each short time",
    "sentence": "Customers were calling every few minutes."
  },
  "few": {
    "simpleMeaning": "A small number",
    "contextMeaning": "A small number of minutes",
    "sentence": "Customers were calling every few minutes."
  },
  "minutes": {
    "simpleMeaning": "A little part of an hour",
    "contextMeaning": "A small amount of time between each call",
    "sentence": "Customers were calling every few minutes."
  },
  "manager": {
    "simpleMeaning": "The person who tells workers what to do",
    "contextMeaning": "Her boss at work",
    "sentence": "Her manager asked her to update a large customer in Singapore."
  },
  "asked": {
    "simpleMeaning": "Wanted something and said it out loud",
    "contextMeaning": "Told her to do something",
    "sentence": "Her manager asked her to update a large customer in Singapore."
  },
  "update": {
    "simpleMeaning": "Tell new information about something",
    "contextMeaning": "Send new information to the customer",
    "sentence": "Her manager asked her to update a large customer in Singapore."
  },
  "large": {
    "simpleMeaning": "Big in size or amount",
    "contextMeaning": "Very big and important",
    "sentence": "Her manager asked her to update a large customer in Singapore."
  },
  "customer": {
    "simpleMeaning": "A person who buys things or uses a service",
    "contextMeaning": "A company that buys from her business",
    "sentence": "Her manager asked her to update a large customer in Singapore."
  },
  "singapore": {
    "simpleMeaning": "A country in Asia",
    "contextMeaning": "The place where the customer is",
    "sentence": "Her manager asked her to update a large customer in Singapore."
  },
  "important": {
    "simpleMeaning": "Very needed or very special",
    "contextMeaning": "Very needed and should not be missed",
    "sentence": "The customer was important."
  },
  "if": {
    "simpleMeaning": "Used when something may happen",
    "contextMeaning": "When this happens, then something else can happen",
    "sentence": "If they felt ignored, they could change suppliers."
  },
  "felt": {
    "simpleMeaning": "Had a feeling inside",
    "contextMeaning": "Thought they were not getting attention",
    "sentence": "If they felt ignored, they could change suppliers."
  },
  "ignored": {
    "simpleMeaning": "Not noticed on purpose",
    "contextMeaning": "Not given attention",
    "sentence": "If they felt ignored, they could change suppliers."
  },
  "change": {
    "simpleMeaning": "Make something different",
    "contextMeaning": "Choose a different company to buy from",
    "sentence": "If they felt ignored, they could change suppliers."
  },
  "suppliers": {
    "simpleMeaning": "People or companies that give things to others",
    "contextMeaning": "Companies that sell them the things they need",
    "sentence": "If they felt ignored, they could change suppliers."
  },
  "write": {
    "simpleMeaning": "Make words on paper or a screen",
    "contextMeaning": "Type words for a message",
    "sentence": "Maria asked an AI tool to write a short update email."
  },
  "short": {
    "simpleMeaning": "Not long",
    "contextMeaning": "Small in length and quick to read",
    "sentence": "Maria asked an AI tool to write a short update email."
  },
  "typed": {
    "simpleMeaning": "Put letters on a computer with fingers",
    "contextMeaning": "Put words into a computer with fingers",
    "sentence": "She typed, “Write a polite message."
  },
  "say": {
    "simpleMeaning": "Use your mouth to tell words",
    "contextMeaning": "Tell the AI to write those words",
    "sentence": "Say the delivery will arrive on Thursday.” The AI wrote a smooth email in seconds."
  },
  "arrive": {
    "simpleMeaning": "Come to a place",
    "contextMeaning": "Get here on Thursday",
    "sentence": "Say the delivery will arrive on Thursday.” The AI wrote a smooth email in seconds."
  },
  "thursday": {
    "simpleMeaning": "The day after Wednesday",
    "contextMeaning": "The day named Thursday",
    "sentence": "Say the delivery will arrive on Thursday.” The AI wrote a smooth email in seconds."
  },
  "wrote": {
    "simpleMeaning": "Made words on paper or screen",
    "contextMeaning": "Made the email text",
    "sentence": "Say the delivery will arrive on Thursday.” The AI wrote a smooth email in seconds."
  },
  "smooth": {
    "simpleMeaning": "Easy and nice, not rough",
    "contextMeaning": "Easy to read and sounds nice",
    "sentence": "Say the delivery will arrive on Thursday.” The AI wrote a smooth email in seconds."
  },
  "sounded": {
    "simpleMeaning": "Seemed when heard by ears",
    "contextMeaning": "Seemed calm and professional when read",
    "sentence": "It sounded calm and professional."
  },
  "calm": {
    "simpleMeaning": "Quiet and not worried",
    "contextMeaning": "Quiet and not upset",
    "sentence": "It sounded calm and professional."
  },
  "professional": {
    "simpleMeaning": "Good for work and serious",
    "contextMeaning": "Good for work and polite",
    "sentence": "It sounded calm and professional."
  },
  "almost": {
    "simpleMeaning": "Very close, but not yet",
    "contextMeaning": "Very close to clicking send",
    "sentence": "Maria almost clicked “send.” Then she looked at the schedule again."
  },
  "clicked": {
    "simpleMeaning": "Pressed a button with a mouse",
    "contextMeaning": "Pressed the send button",
    "sentence": "Maria almost clicked “send.” Then she looked at the schedule again."
  },
  "looked": {
    "simpleMeaning": "Used eyes to see something",
    "contextMeaning": "Checked the schedule with her eyes",
    "sentence": "Maria almost clicked “send.” Then she looked at the schedule again."
  },
  "schedule": {
    "simpleMeaning": "A plan for times and days",
    "contextMeaning": "The plan showing times and days",
    "sentence": "Maria almost clicked “send.” Then she looked at the schedule again."
  },
  "again": {
    "simpleMeaning": "One more time",
    "contextMeaning": "One more time",
    "sentence": "Maria almost clicked “send.” Then she looked at the schedule again."
  },
  "truck": {
    "simpleMeaning": "A big vehicle that carries things",
    "contextMeaning": "A big vehicle carrying things",
    "sentence": "The truck was not arriving Thursday."
  },
  "arriving": {
    "simpleMeaning": "Coming to a place now",
    "contextMeaning": "Coming to the place on Thursday",
    "sentence": "The truck was not arriving Thursday."
  },
  "friday": {
    "simpleMeaning": "The day after Thursday",
    "contextMeaning": "The day after Thursday, when it comes in the morning",
    "sentence": "It was arriving Friday morning."
  },
  "morning": {
    "simpleMeaning": "Early part of the day",
    "contextMeaning": "The early part of Friday",
    "sentence": "It was arriving Friday morning."
  },
  "sent": {
    "simpleMeaning": "Gave something by email or post",
    "contextMeaning": "Emailed it to the customer",
    "sentence": "If Maria had sent the email, the customer might have planned workers and storage for the wrong day."
  },
  "planned": {
    "simpleMeaning": "Thought about what to do first",
    "contextMeaning": "Made a plan for workers and storage",
    "sentence": "If Maria had sent the email, the customer might have planned workers and storage for the wrong day."
  },
  "workers": {
    "simpleMeaning": "People who do a job",
    "contextMeaning": "People who would help with the work",
    "sentence": "If Maria had sent the email, the customer might have planned workers and storage for the wrong day."
  },
  "storage": {
    "simpleMeaning": "A place to keep things safe",
    "contextMeaning": "A place to keep the things",
    "sentence": "If Maria had sent the email, the customer might have planned workers and storage for the wrong day."
  },
  "day": {
    "simpleMeaning": "One part of time with sun and night",
    "contextMeaning": "The wrong time on the calendar",
    "sentence": "If Maria had sent the email, the customer might have planned workers and storage for the wrong day."
  },
  "cost": {
    "simpleMeaning": "Make you pay money",
    "contextMeaning": "Make them lose money and trust",
    "sentence": "That could cost money and trust."
  },
  "money": {
    "simpleMeaning": "Coins and paper used to buy things",
    "contextMeaning": "Cash they may lose",
    "sentence": "That could cost money and trust."
  },
  "trust": {
    "simpleMeaning": "Feeling someone is honest and safe",
    "contextMeaning": "Belief that Maria gives correct information",
    "sentence": "That could cost money and trust."
  },
  "fixed": {
    "simpleMeaning": "Made something right again",
    "contextMeaning": "Changed the date to be correct",
    "sentence": "Maria fixed the date and added one clear detail."
  },
  "added": {
    "simpleMeaning": "Put one more thing in",
    "contextMeaning": "Put in one more clear detail",
    "sentence": "Maria fixed the date and added one clear detail."
  },
  "clear": {
    "simpleMeaning": "Easy to understand",
    "contextMeaning": "Easy to understand and not confusing",
    "sentence": "Maria fixed the date and added one clear detail."
  },
  "detail": {
    "simpleMeaning": "A small part of a thing",
    "contextMeaning": "One small extra piece of information",
    "sentence": "Maria fixed the date and added one clear detail."
  },
  "because": {
    "simpleMeaning": "For this reason; it explains why",
    "contextMeaning": "It gives the reason the time changed",
    "sentence": "She wrote, “Friday, 9 a.m., because the storm closed one highway.” The email took one extra minute."
  },
  "closed": {
    "simpleMeaning": "Not open; shut tight",
    "contextMeaning": "The storm made the road not open",
    "sentence": "She wrote, “Friday, 9 a.m., because the storm closed one highway.” The email took one extra minute."
  },
  "highway": {
    "simpleMeaning": "A big road for cars",
    "contextMeaning": "A large road for driving was blocked",
    "sentence": "She wrote, “Friday, 9 a.m., because the storm closed one highway.” The email took one extra minute."
  },
  "took": {
    "simpleMeaning": "Needed time to do something",
    "contextMeaning": "The email needed one more minute",
    "sentence": "She wrote, “Friday, 9 a.m., because the storm closed one highway.” The email took one extra minute."
  },
  "extra": {
    "simpleMeaning": "More than needed",
    "contextMeaning": "One more minute than usual",
    "sentence": "She wrote, “Friday, 9 a.m., because the storm closed one highway.” The email took one extra minute."
  },
  "minute": {
    "simpleMeaning": "A very short time, sixty seconds",
    "contextMeaning": "A small unit of time",
    "sentence": "She wrote, “Friday, 9 a.m., because the storm closed one highway.” The email took one extra minute."
  },
  "protected": {
    "simpleMeaning": "Kept safe from harm",
    "contextMeaning": "That minute kept the company safe from trouble",
    "sentence": "That minute protected her company’s reputation."
  },
  "reputation": {
    "simpleMeaning": "What people think about someone",
    "contextMeaning": "How people see the company",
    "sentence": "That minute protected her company’s reputation."
  },
  "stories": {
    "simpleMeaning": "Short things people tell or write",
    "contextMeaning": "These kinds of events happen often now",
    "sentence": "Stories like Maria’s are common now."
  },
  "like": {
    "simpleMeaning": "The same as; similar to",
    "contextMeaning": "Similar to Maria’s story",
    "sentence": "Stories like Maria’s are common now."
  },
  "common": {
    "simpleMeaning": "Happening a lot",
    "contextMeaning": "These stories happen often now",
    "sentence": "Stories like Maria’s are common now."
  },
  "many": {
    "simpleMeaning": "A large number of",
    "contextMeaning": "A lot of offices",
    "sentence": "In many offices, people use AI for first drafts."
  },
  "offices": {
    "simpleMeaning": "Places where people work at desks",
    "contextMeaning": "Workplaces where people do jobs",
    "sentence": "In many offices, people use AI for first drafts."
  },
  "people": {
    "simpleMeaning": "Men, women, and children",
    "contextMeaning": "Workers in those offices",
    "sentence": "In many offices, people use AI for first drafts."
  },
  "use": {
    "simpleMeaning": "Do something with",
    "contextMeaning": "They do work with AI",
    "sentence": "In many offices, people use AI for first drafts."
  },
  "first": {
    "simpleMeaning": "Before all others; number one",
    "contextMeaning": "The first version, not the final one",
    "sentence": "In many offices, people use AI for first drafts."
  },
  "drafts": {
    "simpleMeaning": "Early writing, not finished yet",
    "contextMeaning": "Early versions of writing before the final one",
    "sentence": "In many offices, people use AI for first drafts."
  },
  "emails": {
    "simpleMeaning": "Messages sent on a computer or phone",
    "contextMeaning": "Short messages people send by computer",
    "sentence": "They use it for emails, meeting notes, and short reports."
  },
  "meeting": {
    "simpleMeaning": "When people come together to talk",
    "contextMeaning": "A time when people talk together at work",
    "sentence": "They use it for emails, meeting notes, and short reports."
  },
  "notes": {
    "simpleMeaning": "Small pieces of writing to remember things",
    "contextMeaning": "Short writing to help people remember a meeting",
    "sentence": "They use it for emails, meeting notes, and short reports."
  },
  "reports": {
    "simpleMeaning": "Writing that tells about something",
    "contextMeaning": "Short work writing that shares information",
    "sentence": "They use it for emails, meeting notes, and short reports."
  },
  "news": {
    "simpleMeaning": "New things people hear or read about",
    "contextMeaning": "The important new thing people are talking about",
    "sentence": "The news is not that AI exists."
  },
  "exists": {
    "simpleMeaning": "Is real and here",
    "contextMeaning": "Is real and is now here",
    "sentence": "The news is not that AI exists."
  },
  "how": {
    "simpleMeaning": "The way something happens",
    "contextMeaning": "The way companies are doing things differently",
    "sentence": "The news is how companies are changing their training."
  },
  "companies": {
    "simpleMeaning": "Groups of people who work together for business",
    "contextMeaning": "Business groups that employ people",
    "sentence": "The news is how companies are changing their training."
  },
  "changing": {
    "simpleMeaning": "Making something different",
    "contextMeaning": "Making their training different from before",
    "sentence": "The news is how companies are changing their training."
  },
  "training": {
    "simpleMeaning": "Learning how to do a job or skill",
    "contextMeaning": "Learning for work and practice at a company",
    "sentence": "The news is how companies are changing their training."
  },
  "teaching": {
    "simpleMeaning": "Helping someone learn something",
    "contextMeaning": "Showing people how to do something",
    "sentence": "They are teaching people to write better instructions and to check the results."
  },
  "better": {
    "simpleMeaning": "Gooder; more nice or useful",
    "contextMeaning": "More clear and more helpful",
    "sentence": "They are teaching people to write better instructions and to check the results."
  },
  "instructions": {
    "simpleMeaning": "Steps that tell you what to do",
    "contextMeaning": "Clear steps for doing a task",
    "sentence": "They are teaching people to write better instructions and to check the results."
  },
  "results": {
    "simpleMeaning": "What you get after doing something",
    "contextMeaning": "The things they get after checking or making instructions better",
    "sentence": "They are teaching people to write better instructions and to check the results."
  },
  "managers": {
    "simpleMeaning": "People who lead workers",
    "contextMeaning": "People who lead a group and make work choices",
    "sentence": "Managers are learning that speed without judgment can create new risks."
  },
  "learning": {
    "simpleMeaning": "Getting new knowledge or skills",
    "contextMeaning": "Finding out something new and understanding it better",
    "sentence": "Managers are learning that speed without judgment can create new risks."
  },
  "speed": {
    "simpleMeaning": "Doing something very fast",
    "contextMeaning": "Doing work quickly",
    "sentence": "Managers are learning that speed without judgment can create new risks."
  },
  "without": {
    "simpleMeaning": "Not having something",
    "contextMeaning": "Doing it with no careful thinking",
    "sentence": "Managers are learning that speed without judgment can create new risks."
  },
  "judgment": {
    "simpleMeaning": "Good thinking to choose what is right",
    "contextMeaning": "Careful thinking before acting",
    "sentence": "Managers are learning that speed without judgment can create new risks."
  },
  "create": {
    "simpleMeaning": "To make something new",
    "contextMeaning": "To cause new problems to happen",
    "sentence": "Managers are learning that speed without judgment can create new risks."
  },
  "risks": {
    "simpleMeaning": "Things that can hurt you",
    "contextMeaning": "Possible problems or danger",
    "sentence": "Managers are learning that speed without judgment can create new risks."
  },
  "teams": {
    "simpleMeaning": "A group of people working together",
    "contextMeaning": "Groups of people who work together",
    "sentence": "One skill that teams talk about is “leverage.” Leverage means you get more results with the same effort."
  },
  "talk": {
    "simpleMeaning": "To say words to someone",
    "contextMeaning": "Speak about something together",
    "sentence": "One skill that teams talk about is “leverage.” Leverage means you get more results with the same effort."
  },
  "about": {
    "simpleMeaning": "On the topic of something",
    "contextMeaning": "On the topic of late deliveries",
    "sentence": "One skill that teams talk about is “leverage.” Leverage means you get more results with the same effort."
  },
  "leverage": {
    "simpleMeaning": "Using one thing to get a bigger help",
    "contextMeaning": "Getting better results with the same work",
    "sentence": "One skill that teams talk about is “leverage.” Leverage means you get more results with the same effort."
  },
  "means": {
    "simpleMeaning": "Shows what something is",
    "contextMeaning": "Shows the idea of checking facts before using text",
    "sentence": "One skill that teams talk about is “leverage.” Leverage means you get more results with the same effort."
  },
  "more": {
    "simpleMeaning": "A bigger amount",
    "contextMeaning": "A bigger amount of friendliness or emotion",
    "sentence": "One skill that teams talk about is “leverage.” Leverage means you get more results with the same effort."
  },
  "same": {
    "simpleMeaning": "Not different",
    "contextMeaning": "Not different from the other one",
    "sentence": "One skill that teams talk about is “leverage.” Leverage means you get more results with the same effort."
  },
  "effort": {
    "simpleMeaning": "The work and energy you use to do something",
    "contextMeaning": "The work needed to get results",
    "sentence": "One skill that teams talk about is “leverage.” Leverage means you get more results with the same effort."
  },
  "three": {
    "simpleMeaning": "One more than two",
    "contextMeaning": "The number 3 emails or sections",
    "sentence": "Maria can write three emails in the time she used to write one."
  },
  "time": {
    "simpleMeaning": "The minutes and hours when things happen",
    "contextMeaning": "The period Maria needs to write one email",
    "sentence": "Maria can write three emails in the time she used to write one."
  },
  "used": {
    "simpleMeaning": "Did something before, not now",
    "contextMeaning": "Maria wrote one email before, but now she writes more",
    "sentence": "Maria can write three emails in the time she used to write one."
  },
  "price": {
    "simpleMeaning": "What you must give or lose for something",
    "contextMeaning": "The bad cost or problem that comes with leverage",
    "sentence": "But leverage has a price."
  },
  "instruction": {
    "simpleMeaning": "A clear thing that tells you what to do",
    "contextMeaning": "A message that tells the AI what to do",
    "sentence": "If the instruction is vague, the AI may guess."
  },
  "vague": {
    "simpleMeaning": "Not clear; hard to understand",
    "contextMeaning": "Not clear enough, so the AI may not know what to do",
    "sentence": "If the instruction is vague, the AI may guess."
  },
  "guess": {
    "simpleMeaning": "To say an answer without knowing for sure",
    "contextMeaning": "To make a choice without enough information",
    "sentence": "If the instruction is vague, the AI may guess."
  },
  "choose": {
    "simpleMeaning": "To pick one thing from many",
    "contextMeaning": "To pick the wrong date, name, or promise",
    "sentence": "It may choose a wrong date, a wrong name, or a wrong promise."
  },
  "name": {
    "simpleMeaning": "What we call a person or thing",
    "contextMeaning": "The word for a person or thing, like a wrong person’s name",
    "sentence": "It may choose a wrong date, a wrong name, or a wrong promise."
  },
  "promise": {
    "simpleMeaning": "A thing you say you will do",
    "contextMeaning": "A thing the email says it will do, maybe wrongly",
    "sentence": "It may choose a wrong date, a wrong name, or a wrong promise."
  },
  "still": {
    "simpleMeaning": "Even now; it does not stop",
    "contextMeaning": "The email can keep sounding confident, even if it is wrong",
    "sentence": "The email can still sound confident."
  },
  "sound": {
    "simpleMeaning": "To seem a certain way to people",
    "contextMeaning": "To seem sure and strong when read",
    "sentence": "The email can still sound confident."
  },
  "confident": {
    "simpleMeaning": "Feeling sure and not scared",
    "contextMeaning": "Looking sure and certain in the email",
    "sentence": "The email can still sound confident."
  },
  "why": {
    "simpleMeaning": "Asking for the reason",
    "contextMeaning": "The reason prompt quality matters",
    "sentence": "That is why prompt quality matters."
  },
  "prompt": {
    "simpleMeaning": "A message that tells the computer what to do",
    "contextMeaning": "An instruction you give to the AI",
    "sentence": "That is why prompt quality matters."
  },
  "quality": {
    "simpleMeaning": "How good something is",
    "contextMeaning": "How good the prompt is",
    "sentence": "That is why prompt quality matters."
  },
  "matters": {
    "simpleMeaning": "Is important and should be noticed",
    "contextMeaning": "Is important here",
    "sentence": "That is why prompt quality matters."
  },
  "weak": {
    "simpleMeaning": "Not strong or not very good",
    "contextMeaning": "Short and not clear enough",
    "sentence": "A weak prompt is short and unclear."
  },
  "unclear": {
    "simpleMeaning": "Hard to understand",
    "contextMeaning": "Not easy to understand",
    "sentence": "A weak prompt is short and unclear."
  },
  "strong": {
    "simpleMeaning": "Good, clear, and helpful",
    "contextMeaning": "Clear and useful for the AI",
    "sentence": "A strong prompt has a goal, a reader, and limits."
  },
  "goal": {
    "simpleMeaning": "What you want to get",
    "contextMeaning": "The thing you want the AI to do",
    "sentence": "A strong prompt has a goal, a reader, and limits."
  },
  "reader": {
    "simpleMeaning": "The person who reads something",
    "contextMeaning": "The person who will read the message",
    "sentence": "A strong prompt has a goal, a reader, and limits."
  },
  "limits": {
    "simpleMeaning": "Rules that say what is allowed",
    "contextMeaning": "Rules that tell what to do and not do",
    "sentence": "A strong prompt has a goal, a reader, and limits."
  },
  "uses": {
    "simpleMeaning": "Does something with",
    "contextMeaning": "She now works with them",
    "sentence": "Maria now uses prompts like this: “Write a 90-word update for a logistics manager."
  },
  "prompts": {
    "simpleMeaning": "Messages that tell the computer what to do",
    "contextMeaning": "Instructions she gives to the AI",
    "sentence": "Maria now uses prompts like this: “Write a 90-word update for a logistics manager."
  },
  "word": {
    "simpleMeaning": "A small piece of language",
    "contextMeaning": "One piece of text in the answer",
    "sentence": "Maria now uses prompts like this: “Write a 90-word update for a logistics manager."
  },
  "logistics": {
    "simpleMeaning": "Moving things from one place to another",
    "contextMeaning": "Work about moving and delivering goods",
    "sentence": "Maria now uses prompts like this: “Write a 90-word update for a logistics manager."
  },
  "include": {
    "simpleMeaning": "Put something in with other things",
    "contextMeaning": "Add this detail too",
    "sentence": "Include the exact delivery time: Friday 9 a.m."
  },
  "exact": {
    "simpleMeaning": "Just right, with no changes",
    "contextMeaning": "The very same delivery time, not another one",
    "sentence": "Include the exact delivery time: Friday 9 a.m."
  },
  "invent": {
    "simpleMeaning": "Make up something that is not true",
    "contextMeaning": "Make up fake reasons",
    "sentence": "Do not invent reasons.” The AI cannot read her mind."
  },
  "reasons": {
    "simpleMeaning": "Why something happens or is done",
    "contextMeaning": "The why behind something",
    "sentence": "Do not invent reasons.” The AI cannot read her mind."
  },
  "cannot": {
    "simpleMeaning": "Is not able to do something",
    "contextMeaning": "Is not able to",
    "sentence": "Do not invent reasons.” The AI cannot read her mind."
  },
  "read": {
    "simpleMeaning": "Look at words and understand them",
    "contextMeaning": "Understand what someone thinks",
    "sentence": "Do not invent reasons.” The AI cannot read her mind."
  },
  "mind": {
    "simpleMeaning": "The part of you that thinks and feels",
    "contextMeaning": "Her thoughts and feelings",
    "sentence": "Do not invent reasons.” The AI cannot read her mind."
  },
  "give": {
    "simpleMeaning": "Put something into someone’s hand or place",
    "contextMeaning": "Provide something for it",
    "sentence": "She must give it a target."
  },
  "target": {
    "simpleMeaning": "The thing you want to hit or reach",
    "contextMeaning": "A clear goal to aim for",
    "sentence": "She must give it a target."
  },
  "learned": {
    "simpleMeaning": "Got new knowledge or skill",
    "contextMeaning": "Found out how to do it",
    "sentence": "Maria also learned to break big tasks into smaller steps."
  },
  "break": {
    "simpleMeaning": "Make one thing into smaller parts",
    "contextMeaning": "Split a big job into little parts",
    "sentence": "Maria also learned to break big tasks into smaller steps."
  },
  "tasks": {
    "simpleMeaning": "Jobs you need to do",
    "contextMeaning": "Jobs Maria needs to finish",
    "sentence": "Maria also learned to break big tasks into smaller steps."
  },
  "smaller": {
    "simpleMeaning": "Not as big as another thing",
    "contextMeaning": "Less big and easier to handle",
    "sentence": "Maria also learned to break big tasks into smaller steps."
  },
  "steps": {
    "simpleMeaning": "Small parts of doing something",
    "contextMeaning": "Small actions to do one by one",
    "sentence": "Maria also learned to break big tasks into smaller steps."
  },
  "wanted": {
    "simpleMeaning": "Hoped to have or get something",
    "contextMeaning": "Needed or asked for",
    "sentence": "One day, her manager wanted a short report about late deliveries."
  },
  "report": {
    "simpleMeaning": "A short text that tells facts",
    "contextMeaning": "A short text about late deliveries",
    "sentence": "One day, her manager wanted a short report about late deliveries."
  },
  "late": {
    "simpleMeaning": "Not on time",
    "contextMeaning": "Arriving after the right time",
    "sentence": "One day, her manager wanted a short report about late deliveries."
  },
  "deliveries": {
    "simpleMeaning": "Things brought to people or places",
    "contextMeaning": "Packages or goods that arrived late",
    "sentence": "One day, her manager wanted a short report about late deliveries."
  },
  "full": {
    "simpleMeaning": "With everything inside; not empty",
    "contextMeaning": "The whole report, not a short part",
    "sentence": "At first, Maria asked the AI for the full report."
  },
  "answer": {
    "simpleMeaning": "What you say to a question",
    "contextMeaning": "The reply given by the AI",
    "sentence": "The answer was too general."
  },
  "general": {
    "simpleMeaning": "Not about one small thing",
    "contextMeaning": "Too broad, not specific enough",
    "sentence": "The answer was too general."
  },
  "simple": {
    "simpleMeaning": "Easy to do or understand",
    "contextMeaning": "Easy and not complicated",
    "sentence": "Now she uses a simple workflow."
  },
  "workflow": {
    "simpleMeaning": "The steps you do in order",
    "contextMeaning": "A set way to do the task",
    "sentence": "Now she uses a simple workflow."
  },
  "pastes": {
    "simpleMeaning": "Puts copied words or pictures somewhere",
    "contextMeaning": "She puts the copied data into the AI",
    "sentence": "First she pastes real data from the tracking sheet."
  },
  "data": {
    "simpleMeaning": "Facts and numbers about something",
    "contextMeaning": "Information from the tracking sheet",
    "sentence": "First she pastes real data from the tracking sheet."
  },
  "tracking": {
    "simpleMeaning": "Watching where something goes",
    "contextMeaning": "Showing where the deliveries are and when",
    "sentence": "First she pastes real data from the tracking sheet."
  },
  "sheet": {
    "simpleMeaning": "A flat paper or page",
    "contextMeaning": "A page with the delivery information",
    "sentence": "First she pastes real data from the tracking sheet."
  },
  "asks": {
    "simpleMeaning": "Says you want something",
    "contextMeaning": "She tells the AI what she wants",
    "sentence": "Then she asks for three sections: the main problem, the cause, and the next steps."
  },
  "sections": {
    "simpleMeaning": "Small parts of a bigger thing",
    "contextMeaning": "Three separate parts of the report",
    "sentence": "Then she asks for three sections: the main problem, the cause, and the next steps."
  },
  "main": {
    "simpleMeaning": "Most important; biggest one",
    "contextMeaning": "The most important problem",
    "sentence": "Then she asks for three sections: the main problem, the cause, and the next steps."
  },
  "cause": {
    "simpleMeaning": "The thing that makes something happen",
    "contextMeaning": "Why the problem happened",
    "sentence": "Then she asks for three sections: the main problem, the cause, and the next steps."
  },
  "next": {
    "simpleMeaning": "Coming after this one",
    "contextMeaning": "The actions to do after the problem and cause",
    "sentence": "Then she asks for three sections: the main problem, the cause, and the next steps."
  },
  "after": {
    "simpleMeaning": "Later in time; next thing happens",
    "contextMeaning": "Later than that moment; then she asks the AI",
    "sentence": "After that, she asks the AI to rewrite each section in clearer English."
  },
  "rewrite": {
    "simpleMeaning": "Write again in a new way",
    "contextMeaning": "Write the same thing again with easier words",
    "sentence": "After that, she asks the AI to rewrite each section in clearer English."
  },
  "each": {
    "simpleMeaning": "Every one, one by one",
    "contextMeaning": "Every single section, not just some of them",
    "sentence": "After that, she asks the AI to rewrite each section in clearer English."
  },
  "section": {
    "simpleMeaning": "One small part of something bigger",
    "contextMeaning": "One part of the writing",
    "sentence": "After that, she asks the AI to rewrite each section in clearer English."
  },
  "clearer": {
    "simpleMeaning": "Easier to understand and see",
    "contextMeaning": "Easier for people to understand",
    "sentence": "After that, she asks the AI to rewrite each section in clearer English."
  },
  "english": {
    "simpleMeaning": "A language many people speak and write",
    "contextMeaning": "The language used in the sentence and stories",
    "sentence": "After that, she asks the AI to rewrite each section in clearer English."
  },
  "loop": {
    "simpleMeaning": "A round shape or repeating path",
    "contextMeaning": "A small repeating step used to make the text better",
    "sentence": "She also uses a small “loop” to improve the text."
  },
  "improve": {
    "simpleMeaning": "Make something better than before",
    "contextMeaning": "Make the text better and easier to use",
    "sentence": "She also uses a small “loop” to improve the text."
  },
  "text": {
    "simpleMeaning": "Words written on paper or a screen",
    "contextMeaning": "The writing she is working on",
    "sentence": "She also uses a small “loop” to improve the text."
  },
  "reviews": {
    "simpleMeaning": "Looks at something again carefully",
    "contextMeaning": "Checks the work again and again",
    "sentence": "She asks, she reviews, and she asks again."
  },
  "version": {
    "simpleMeaning": "One form of something written or made",
    "contextMeaning": "One copy of the writing after changes",
    "sentence": "The first version is only a draft."
  },
  "draft": {
    "simpleMeaning": "A first try, not finished yet",
    "contextMeaning": "The first not-finished version of the writing",
    "sentence": "The first version is only a draft."
  },
  "second": {
    "simpleMeaning": "Number two; coming after the first",
    "contextMeaning": "The next version, number two",
    "sentence": "The second version becomes clearer."
  },
  "becomes": {
    "simpleMeaning": "Starts to be something new",
    "contextMeaning": "Starts to get clearer",
    "sentence": "The second version becomes clearer."
  },
  "third": {
    "simpleMeaning": "Number three; after the second",
    "contextMeaning": "The next version, number three",
    "sentence": "The third version becomes shorter."
  },
  "shorter": {
    "simpleMeaning": "Not as long as before",
    "contextMeaning": "It becomes not as long",
    "sentence": "The third version becomes shorter."
  },
  "make": {
    "simpleMeaning": "Do something so it becomes different",
    "contextMeaning": "Change it into a friendlier or less emotional version",
    "sentence": "Maria might say, “Make this more friendly,” or “Make it less emotional,” depending on the customer."
  },
  "friendly": {
    "simpleMeaning": "Kind and nice to people",
    "contextMeaning": "It sounds kind and nice",
    "sentence": "Maria might say, “Make this more friendly,” or “Make it less emotional,” depending on the customer."
  },
  "less": {
    "simpleMeaning": "A smaller amount",
    "contextMeaning": "Not as emotional as before",
    "sentence": "Maria might say, “Make this more friendly,” or “Make it less emotional,” depending on the customer."
  },
  "emotional": {
    "simpleMeaning": "Showing strong feelings",
    "contextMeaning": "Full of strong feelings",
    "sentence": "Maria might say, “Make this more friendly,” or “Make it less emotional,” depending on the customer."
  },
  "depending": {
    "simpleMeaning": "Changing because of something else",
    "contextMeaning": "It changes because of the customer",
    "sentence": "Maria might say, “Make this more friendly,” or “Make it less emotional,” depending on the customer."
  },
  "saves": {
    "simpleMeaning": "Uses less time or work",
    "contextMeaning": "It helps use less time",
    "sentence": "This saves time, but it still needs her eyes and her choices."
  },
  "needs": {
    "simpleMeaning": "Must have something",
    "contextMeaning": "It still must have her help and decisions",
    "sentence": "This saves time, but it still needs her eyes and her choices."
  },
  "eyes": {
    "simpleMeaning": "The parts you use to see",
    "contextMeaning": "She must look at it carefully",
    "sentence": "This saves time, but it still needs her eyes and her choices."
  },
  "choices": {
    "simpleMeaning": "Things you can pick from",
    "contextMeaning": "She must decide what to pick",
    "sentence": "This saves time, but it still needs her eyes and her choices."
  },
  "most": {
    "simpleMeaning": "More than all the others",
    "contextMeaning": "The biggest or top one",
    "sentence": "The most important habit is verification."
  },
  "habit": {
    "simpleMeaning": "Something you do again and again",
    "contextMeaning": "A good thing to do every day",
    "sentence": "The most important habit is verification."
  },
  "verification": {
    "simpleMeaning": "Checking if something is true",
    "contextMeaning": "Checking if the information is right",
    "sentence": "The most important habit is verification."
  },
  "checks": {
    "simpleMeaning": "Looks carefully to see if it is right",
    "contextMeaning": "She looks carefully at the facts first",
    "sentence": "Maria checks facts before she sends anything."
  },
  "facts": {
    "simpleMeaning": "Things that are true",
    "contextMeaning": "True information like dates and numbers",
    "sentence": "Maria checks facts before she sends anything."
  },
  "before": {
    "simpleMeaning": "Earlier than something else happens",
    "contextMeaning": "First, and only then she sends it",
    "sentence": "Maria checks facts before she sends anything."
  },
  "sends": {
    "simpleMeaning": "Gives or moves something to someone",
    "contextMeaning": "She gives the message to someone",
    "sentence": "Maria checks facts before she sends anything."
  },
  "anything": {
    "simpleMeaning": "Any thing at all",
    "contextMeaning": "She does not send any message or item",
    "sentence": "Maria checks facts before she sends anything."
  },
  "dates": {
    "simpleMeaning": "Day numbers on a calendar",
    "contextMeaning": "The day numbers in the message",
    "sentence": "She checks dates, names, prices, and promises."
  },
  "names": {
    "simpleMeaning": "Words for people or things",
    "contextMeaning": "The words that tell who someone is",
    "sentence": "She checks dates, names, prices, and promises."
  },
  "prices": {
    "simpleMeaning": "How much money something costs",
    "contextMeaning": "The money amounts in the message",
    "sentence": "She checks dates, names, prices, and promises."
  },
  "promises": {
    "simpleMeaning": "Things you say you will do",
    "contextMeaning": "Things someone said they will do",
    "sentence": "She checks dates, names, prices, and promises."
  },
  "when": {
    "simpleMeaning": "At the time something happens",
    "contextMeaning": "At the time AI writes, and also at the time it is wrong",
    "sentence": "When AI writes, it can sound sure even when it is wrong."
  },
  "writes": {
    "simpleMeaning": "Puts words on paper or screen",
    "contextMeaning": "Makes text with words",
    "sentence": "When AI writes, it can sound sure even when it is wrong."
  },
  "sure": {
    "simpleMeaning": "Feeling very certain",
    "contextMeaning": "It sounds very certain",
    "sentence": "When AI writes, it can sound sure even when it is wrong."
  },
  "even": {
    "simpleMeaning": "Used to show something surprising",
    "contextMeaning": "Also in the surprising case that it is wrong",
    "sentence": "When AI writes, it can sound sure even when it is wrong."
  },
  "rule": {
    "simpleMeaning": "A thing you must always do",
    "contextMeaning": "Maria always checks numbers if they appear",
    "sentence": "Maria has one rule: if the message contains a number, she checks it in the company system."
  },
  "contains": {
    "simpleMeaning": "Has something inside it",
    "contextMeaning": "Has a number inside it",
    "sentence": "Maria has one rule: if the message contains a number, she checks it in the company system."
  },
  "number": {
    "simpleMeaning": "A counting word like 1 or 20",
    "contextMeaning": "A digit or counting word in the message",
    "sentence": "Maria has one rule: if the message contains a number, she checks it in the company system."
  },
  "system": {
    "simpleMeaning": "A group of parts that work together",
    "contextMeaning": "The company computer place that stores facts",
    "sentence": "Maria has one rule: if the message contains a number, she checks it in the company system."
  },
  "reason": {
    "simpleMeaning": "Why something happens or is done",
    "contextMeaning": "The cause or explanation for it",
    "sentence": "If it contains a reason, she checks it with the operations team."
  },
  "operations": {
    "simpleMeaning": "The work a group does every day",
    "contextMeaning": "The work team that handles daily tasks",
    "sentence": "If it contains a reason, she checks it with the operations team."
  },
  "team": {
    "simpleMeaning": "People working together",
    "contextMeaning": "The group of workers she asks",
    "sentence": "If it contains a reason, she checks it with the operations team."
  },
  "helps": {
    "simpleMeaning": "Makes something easier for someone",
    "contextMeaning": "Makes writing easier for her",
    "sentence": "AI helps her write."
  },
  "final": {
    "simpleMeaning": "Last and most important",
    "contextMeaning": "The last and most important answer",
    "sentence": "It does not give the final truth."
  },
  "truth": {
    "simpleMeaning": "What is really real",
    "contextMeaning": "The real answer, not a perfect one",
    "sentence": "It does not give the final truth."
  },
  "win": {
    "simpleMeaning": "To be the best and get first place",
    "contextMeaning": "To get first place",
    "sentence": "Maria did not win because she typed faster."
  },
  "faster": {
    "simpleMeaning": "Moving or doing something more quickly",
    "contextMeaning": "More quickly than before",
    "sentence": "Maria did not win because she typed faster."
  },
  "won": {
    "simpleMeaning": "Got first place or succeeded",
    "contextMeaning": "Got first place",
    "sentence": "She won because she stayed in control."
  },
  "stayed": {
    "simpleMeaning": "Kept being in one place or way",
    "contextMeaning": "Kept calm and in control",
    "sentence": "She won because she stayed in control."
  },
  "control": {
    "simpleMeaning": "Being able to manage something well",
    "contextMeaning": "Being calm and managing herself well",
    "sentence": "She won because she stayed in control."
  },
  "guide": {
    "simpleMeaning": "To show the way or help lead",
    "contextMeaning": "Help direct what it does",
    "sentence": "AI can give you a clean draft, but you must guide it."
  },
  "test": {
    "simpleMeaning": "To try something and see if it works",
    "contextMeaning": "Check it using real facts",
    "sentence": "You must also test it against real information."
  },
  "against": {
    "simpleMeaning": "Compared with something else",
    "contextMeaning": "Checked by comparing with real facts",
    "sentence": "You must also test it against real information."
  },
  "information": {
    "simpleMeaning": "Facts and details about something",
    "contextMeaning": "Real facts and details",
    "sentence": "You must also test it against real information."
  },
  "useful": {
    "simpleMeaning": "Good for helping you do things",
    "contextMeaning": "Helping AI do a good job for you",
    "sentence": "When you do that, AI becomes a useful partner, not a risky shortcut."
  },
  "partner": {
    "simpleMeaning": "Someone who works with you",
    "contextMeaning": "Something that helps you work together",
    "sentence": "When you do that, AI becomes a useful partner, not a risky shortcut."
  },
  "risky": {
    "simpleMeaning": "May cause trouble or danger",
    "contextMeaning": "May cause problems or mistakes",
    "sentence": "When you do that, AI becomes a useful partner, not a risky shortcut."
  },
  "shortcut": {
    "simpleMeaning": "A fast way to do something",
    "contextMeaning": "A fast way that may not be safe",
    "sentence": "When you do that, AI becomes a useful partner, not a risky shortcut."
  },
  "try": {
    "simpleMeaning": "Do something to see what happens",
    "contextMeaning": "Do one small thing now",
    "sentence": "Try one small habit today."
  },
  "today": {
    "simpleMeaning": "This day, now",
    "contextMeaning": "On this day, not later",
    "sentence": "Try one small habit today."
  },
  "want": {
    "simpleMeaning": "Wish to have or do something",
    "contextMeaning": "If you wish for more simple stories",
    "sentence": "If you want more simple English stories like this, visit ovi english dot com."
  },
  "visit": {
    "simpleMeaning": "Go to see a place or person",
    "contextMeaning": "Go to that website",
    "sentence": "If you want more simple English stories like this, visit ovi english dot com."
  },
  "ovi": {
    "simpleMeaning": "A name for a person or thing",
    "contextMeaning": "The name in the website address",
    "sentence": "If you want more simple English stories like this, visit ovi english dot com."
  },
  "dot": {
    "simpleMeaning": "A very small round mark",
    "contextMeaning": "The small mark in the website address",
    "sentence": "If you want more simple English stories like this, visit ovi english dot com."
  },
  "com": {
    "simpleMeaning": "Part of a website name",
    "contextMeaning": "The ending part of the website address",
    "sentence": "If you want more simple English stories like this, visit ovi english dot com."
  },
  "opening": {
    "simpleMeaning": "The start of something",
    "contextMeaning": "The first part of the text",
    "sentence": "[OPENING] You finish work at 6 p.m."
  },
  "story": {
    "simpleMeaning": "Something people tell or write about events",
    "contextMeaning": "A news report about Maria",
    "sentence": "[NEWS STORY] Last week, Maria, who works at a small shipping company in Manila, had a busy afternoon."
  },
  "practice": {
    "simpleMeaning": "Doing something again to learn it",
    "contextMeaning": "An exercise to answer and learn",
    "sentence": "[PRACTICE] QUESTION: What problem did Maria notice in the AI email?"
  },
  "question": {
    "simpleMeaning": "A sentence asking for an answer",
    "contextMeaning": "The thing asking about Maria's problem",
    "sentence": "[PRACTICE] QUESTION: What problem did Maria notice in the AI email?"
  },
  "what": {
    "simpleMeaning": "Used to ask about a thing or idea",
    "contextMeaning": "Asks about the problem Maria saw in the email",
    "sentence": "[PRACTICE] QUESTION: What problem did Maria notice in the AI email?"
  },
  "damage": {
    "simpleMeaning": "To hurt something or make it worse",
    "contextMeaning": "Could hurt people’s trust in the customer",
    "sentence": "QUESTION: Why could one wrong date damage trust?"
  },
  "plan": {
    "simpleMeaning": "To think ahead and decide what to do",
    "contextMeaning": "Decide staff and storage for the wrong day",
    "sentence": "ANSWER: The customer might plan staff and storage for the wrong day."
  },
  "staff": {
    "simpleMeaning": "The people who work in a place",
    "contextMeaning": "Workers the customer may schedule for that day",
    "sentence": "ANSWER: The customer might plan staff and storage for the wrong day."
  },
  "easier": {
    "simpleMeaning": "Not hard; simple to do",
    "contextMeaning": "Smaller steps are simpler to control and check",
    "sentence": "ANSWER: Smaller steps are easier to control, improve, and check."
  },
  "mean": {
    "simpleMeaning": "To show or tell an idea",
    "contextMeaning": "Asks what verification is in AI work",
    "sentence": "QUESTION: What does verification mean in AI work?"
  },
  "checking": {
    "simpleMeaning": "Looking carefully to see if it is right",
    "contextMeaning": "Looking at facts before using the text",
    "sentence": "ANSWER: It means checking facts like dates and numbers before you use the text."
  },
  "numbers": {
    "simpleMeaning": "Counting words like 1, 2, 3",
    "contextMeaning": "Things like dates and counting values in the text",
    "sentence": "ANSWER: It means checking facts like dates and numbers before you use the text."
  },
  "closing": {
    "simpleMeaning": "At the end; finishing something",
    "contextMeaning": "The last part says Maria lost because she typed faster",
    "sentence": "[CLOSING] Maria did not win because she typed faster."
  }
}